README.rst
setup.py
notetxt/__init__.py
notetxt.egg-info/PKG-INFO
notetxt.egg-info/SOURCES.txt
notetxt.egg-info/dependency_links.txt
notetxt.egg-info/not-zip-safe
notetxt.egg-info/top_level.txt